{
  "title": "EVM Swap - Buy $100 ETH on Base if ETH below $1800",
  "graph": {
    "nodes": [
      { "id": "eth-below-1800", "kind": "signal", "subtype": "price_threshold",
        "config": { "symbol": "ETH", "operator": "<", "threshold": "1800" }, "enabled": true },
      { "id": "buy-eth-on-base", "kind": "action", "subtype": "swap",
        "config": { "from_asset": "USDC", "to_asset": "ETH", "amount": "100", "chain": "base" }, "enabled": true }
    ],
    "edges": [ { "from": "eth-below-1800", "to": "buy-eth-on-base" } ]
  }
}
